teslemetry_stream/__init__.py
teslemetry_stream/const.py
teslemetry_stream/exception.py
teslemetry_stream/py.typed
teslemetry_stream/stream.py
teslemetry_stream/vehicle.py
teslemetry_stream-0.9.0.dist-info/licenses/LICENSE
teslemetry_stream-0.9.0.dist-info/METADATA
teslemetry_stream-0.9.0.dist-info/WHEEL
teslemetry_stream-0.9.0.dist-info/top_level.txt
teslemetry_stream-0.9.0.dist-info/RECORD
