Metadata-Version: 2.4
Name: teslemetry_stream
Version: 0.9.0
Summary: Teslemetry Streaming API library for Python
Author-email: Brett Adams <hello@teslemetry.com>
License-Expression: Apache-2.0
Project-URL: Source code, https://github.com/Teslemetry/teslemetry_stream
Classifier: Development Status :: 4 - Beta
Classifier: Programming Language :: Python :: 3
Classifier: Operating System :: OS Independent
Requires-Python: >=3.9
License-File: LICENSE
Requires-Dist: aiohttp
Dynamic: license-file
